{"sample1":{"_complementStrand":["T","T","G","C","G","T","C","C","C","T","C","A","G","A","C"],"_dna":["A","A","C","G","C","A","G","G","G","A","G","T","C","T","G"],"dnaLength":15,"specimenNum":0},"sample2":{"_complementStrand":["G","G","G","G","C","G","T","C","A","A","C","G","A","T","A"],"_dna":["C","C","C","C","G","C","A","G","T","T","G","C","T","A","T"],"dnaLength":15,"specimenNum":2},"sample3":{"_complementStrand":["G","T","G","G","C","A","C","C","C","A","C","C","T","T","G"],"_dna":["C","A","C","C","G","T","G","G","G","T","G","G","A","A","C"],"dnaLength":15,"specimenNum":3},"sample4":{"_complementStrand":["G","T","T","C","A","A","C","C","A","G","G","C","G","G","T"],"_dna":["C","A","A","G","T","T","G","G","T","C","C","G","C","C","A"],"dnaLength":15,"specimenNum":11},"sample5":{"_complementStrand":["C","T","T","C","C","T","C","C","C","G","G","G","C","T","A"],"_dna":["G","A","A","G","G","A","G","G","G","C","C","C","G","A","T"],"dnaLength":15,"specimenNum":13},"sample6":{"_complementStrand":["C","T","G","A","T","C","G","A","G","A","G","G","C","A","C"],"_dna":["G","A","C","T","A","G","C","T","C","T","C","C","G","T","G"],"dnaLength":15,"specimenNum":14},"sample7":{"_complementStrand":["G","C","G","T","G","T","C","G","C","C","T","T","T","T","C"],"_dna":["C","G","C","A","C","A","G","C","G","G","A","A","A","A","G"],"dnaLength":15,"specimenNum":17},"sample8":{"_complementStrand":["C","A","G","G","C","C","G","A","T","G","C","G","T","G","G"],"_dna":["G","T","C","C","G","G","C","T","A","C","G","C","A","C","C"],"dnaLength":15,"specimenNum":22},"sample9":{"_complementStrand":["C","G","T","A","C","A","G","G","T","C","G","T","G","G","T"],"_dna":["G","C","A","T","G","T","C","C","A","G","C","A","C","C","A"],"dnaLength":15,"specimenNum":26},"sample10":{"_complementStrand":["G","C","C","G","C","A","G","G","C","A","A","T","T","G","A"],"_dna":["C","G","G","C","G","T","C","C","G","T","T","A","A","C","T"],"dnaLength":15,"specimenNum":31},"sample11":{"_complementStrand":["T","G","A","A","C","G","A","G","C","T","C","C","T","C","C"],"_dna":["A","C","T","T","G","C","T","C","G","A","G","G","A","G","G"],"dnaLength":15,"specimenNum":48},"sample12":{"_complementStrand":["G","T","T","G","G","C","C","G","G","A","A","T","G","A","C"],"_dna":["C","A","A","C","C","G","G","C","C","T","T","A","C","T","G"],"dnaLength":15,"specimenNum":49},"sample13":{"_complementStrand":["G","C","A","A","C","G","G","G","G","G","T","G","A","G","A"],"_dna":["C","G","T","T","G","C","C","C","C","C","A","C","T","C","T"],"dnaLength":15,"specimenNum":50},"sample14":{"_complementStrand":["T","C","A","T","T","G","C","A","A","G","G","C","C","C","C"],"_dna":["A","G","T","A","A","C","G","T","T","C","C","G","G","G","G"],"dnaLength":15,"specimenNum":52},"sample15":{"_complementStrand":["G","C","T","C","G","A","A","C","G","T","G","A","A","C","G"],"_dna":["C","G","A","G","C","T","T","G","C","A","C","T","T","G","C"],"dnaLength":15,"specimenNum":56},"sample16":{"_complementStrand":["T","A","G","C","C","G","C","C","G","A","A","G","A","G","C"],"_dna":["A","T","C","G","G","C","G","G","C","T","T","C","T","C","G"],"dnaLength":15,"specimenNum":57},"sample17":{"_complementStrand":["T","C","G","C","A","G","G","A","T","G","C","G","G","A","T"],"_dna":["A","G","C","G","T","C","C","T","A","C","G","C","C","T","A"],"dnaLength":15,"specimenNum":60},"sample18":{"_complementStrand":["A","A","C","G","A","C","T","C","A","C","G","A","C","G","C"],"_dna":["T","T","G","C","T","G","A","G","T","G","C","T","G","C","G"],"dnaLength":15,"specimenNum":61},"sample19":{"_complementStrand":["A","C","C","G","A","A","C","G","C","C","G","C","T","A","C"],"_dna":["T","G","G","C","T","T","G","C","G","G","C","G","A","T","G"],"dnaLength":15,"specimenNum":67},"sample20":{"_complementStrand":["G","G","G","T","G","G","C","G","T","G","A","C","C","T","G"],"_dna":["C","C","C","A","C","C","G","C","A","C","T","G","G","A","C"],"dnaLength":15,"specimenNum":68},"sample21":{"_complementStrand":["C","G","C","G","C","T","C","G","C","A","T","C","T","T","T"],"_dna":["G","C","G","C","G","A","G","C","G","T","A","G","A","A","A"],"dnaLength":15,"specimenNum":69},"sample22":{"_complementStrand":["G","C","C","T","G","G","T","C","G","C","C","A","G","C","C"],"_dna":["C","G","G","A","C","C","A","G","C","G","G","T","C","G","G"],"dnaLength":15,"specimenNum":70},"sample23":{"_complementStrand":["C","C","G","G","G","C","G","G","G","A","T","T","C","A","G"],"_dna":["G","G","C","C","C","G","C","C","C","T","A","A","G","T","C"],"dnaLength":15,"specimenNum":72},"sample24":{"_complementStrand":["G","G","A","A","T","C","A","C","G","C","T","C","C","A","C"],"_dna":["C","C","T","T","A","G","T","G","C","G","A","G","G","T","G"],"dnaLength":15,"specimenNum":75},"sample25":{"_complementStrand":["C","C","C","G","A","T","C","G","T","C","T","C","C","T","T"],"_dna":["G","G","G","C","T","A","G","C","A","G","A","G","G","A","A"],"dnaLength":15,"specimenNum":78},"sample26":{"_complementStrand":["T","G","T","A","G","C","T","C","G","A","C","C","G","G","A"],"_dna":["A","C","A","T","C","G","A","G","C","T","G","G","C","C","T"],"dnaLength":15,"specimenNum":88},"sample27":{"_complementStrand":["A","C","T","C","A","T","A","C","G","G","T","G","G","G","G"],"_dna":["T","G","A","G","T","A","T","G","C","C","A","C","C","C","C"],"dnaLength":15,"specimenNum":91},"sample28":{"_complementStrand":["T","G","C","C","A","C","C","T","A","C","C","T","G","A","G"],"_dna":["A","C","G","G","T","G","G","A","T","G","G","A","C","T","C"],"dnaLength":15,"specimenNum":93},"sample29":{"_complementStrand":["C","G","G","A","T","C","C","C","C","T","G","T","T","G","T"],"_dna":["G","C","C","T","A","G","G","G","G","A","C","A","A","C","A"],"dnaLength":15,"specimenNum":97},"sample30":{"_complementStrand":["A","G","A","G","G","C","T","C","A","G","G","G","G","C","A"],"_dna":["T","C","T","C","C","G","A","G","T","C","C","C","C","G","T"],"dnaLength":15,"specimenNum":99}}